proof_parser/__init__.py
proof_parser/exceptions.py
proof_parser/models.py
proof_parser/parser.py
proof_report_parser-0.9.8.dist-info/LICENSE
proof_report_parser-0.9.8.dist-info/METADATA
proof_report_parser-0.9.8.dist-info/WHEEL
proof_report_parser-0.9.8.dist-info/top_level.txt
proof_report_parser-0.9.8.dist-info/RECORD
